{"PartesCancion":[{"Texto":"Intro: ","Notas":[]},{"Texto":"","Notas":[{"Nombre":"MIm","NumeroNota":7,"NombreNota":"MI","Mayor":false,"NumeroModificador":0,"Duracion":0},{"Nombre":"MIm","NumeroNota":7,"NombreNota":"MI","Mayor":false,"NumeroModificador":0,"Duracion":0}]},{"Texto":"\n   Cuando rio de placer\ny me quedo solo suspirando formas\n       ","Notas":[]},{"Texto":"","Notas":[{"Nombre":"LA","NumeroNota":0,"NombreNota":"LA","Mayor":true,"NumeroModificador":0,"Duracion":0}]},{"Texto":"\nde humo\n\n\n","Notas":[]},{"Texto":"","Notas":[{"Nombre":"SOL","NumeroNota":10,"NombreNota":"SOL","Mayor":true,"NumeroModificador":0,"Duracion":0},{"Nombre":"DO","NumeroNota":3,"NombreNota":"DO","Mayor":true,"NumeroModificador":0,"Duracion":0}]},{"Texto":"\n   Dulce criatura\n","Notas":[]},{"Texto":"","Notas":[{"Nombre":"SOL","NumeroNota":10,"NombreNota":"SOL","Mayor":true,"NumeroModificador":0,"Duracion":0},{"Nombre":"DO","NumeroNota":3,"NombreNota":"DO","Mayor":true,"NumeroModificador":0,"Duracion":0}]},{"Texto":"\n   nunca estas segura\n","Notas":[]},{"Texto":"","Notas":[{"Nombre":"SOL","NumeroNota":10,"NombreNota":"SOL","Mayor":true,"NumeroModificador":0,"Duracion":0},{"Nombre":"FA","NumeroNota":8,"NombreNota":"FA","Mayor":true,"NumeroModificador":0,"Duracion":0}]},{"Texto":"\n   soy tan dependiente\n","Notas":[]},{"Texto":"","Notas":[{"Nombre":"MIm","NumeroNota":7,"NombreNota":"MI","Mayor":false,"NumeroModificador":0,"Duracion":0}]},{"Texto":"\n de tu amor\n\n\nNo me sigas, no se donde voy;\nlas cenizan vuelan en un claroscuro\n","Notas":[]},{"Texto":"","Notas":[{"Nombre":"Em","NumeroNota":7,"NombreNota":"E","Mayor":false,"NumeroModificador":0,"Duracion":0}]},{"Texto":"\nCuando rio de placer\n\ny me quedo solo suspirando formas de humo...\n\n","Notas":[]},{"Texto":"","Notas":[{"Nombre":"G","NumeroNota":10,"NombreNota":"G","Mayor":true,"NumeroModificador":0,"Duracion":0},{"Nombre":"C","NumeroNota":3,"NombreNota":"C","Mayor":true,"NumeroModificador":0,"Duracion":0},{"Nombre":"G/B","NumeroNota":2,"NombreNota":"B","Mayor":true,"NumeroModificador":0,"Duracion":0}]},{"Texto":"\nDulce criatura\n         ","Notas":[]},{"Texto":"","Notas":[{"Nombre":"Am","NumeroNota":0,"NombreNota":"A","Mayor":false,"NumeroModificador":0,"Duracion":0},{"Nombre":"G","NumeroNota":10,"NombreNota":"G","Mayor":true,"NumeroModificador":0,"Duracion":0}]},{"Texto":"\nnunca estas segura\n           ","Notas":[]},{"Texto":"","Notas":[{"Nombre":"F","NumeroNota":8,"NombreNota":"F","Mayor":true,"NumeroModificador":0,"Duracion":0},{"Nombre":"Em","NumeroNota":7,"NombreNota":"E","Mayor":false,"NumeroModificador":0,"Duracion":0}]},{"Texto":"\ny soy tan dependiente de tu amor.\n\n","Notas":[]},{"Texto":"","Notas":[{"Nombre":"Em","NumeroNota":7,"NombreNota":"E","Mayor":false,"NumeroModificador":0,"Duracion":0}]},{"Texto":"\nNo me sigas, no se donde voy;\n\nlas cenizas vuelan en un claroscuro\n\ny me nublan.\n\n","Notas":[]},{"Texto":"","Notas":[{"Nombre":"G","NumeroNota":10,"NombreNota":"G","Mayor":true,"NumeroModificador":0,"Duracion":0},{"Nombre":"C","NumeroNota":3,"NombreNota":"C","Mayor":true,"NumeroModificador":0,"Duracion":0},{"Nombre":"G/B","NumeroNota":2,"NombreNota":"B","Mayor":true,"NumeroModificador":0,"Duracion":0},{"Nombre":"Am","NumeroNota":0,"NombreNota":"A","Mayor":false,"NumeroModificador":0,"Duracion":0},{"Nombre":"G","NumeroNota":10,"NombreNota":"G","Mayor":true,"NumeroModificador":0,"Duracion":0}]},{"Texto":"Uno de los de soda que a mi m\u00E1s me gusta, en tabs de bajo para uds.\r\nes muy facil sale de una si lo tocan con el disco... soy m\u00FAsico de C\u00F3rdoba Argentina\r\nEstoy buscando bajista interesado en armar banda de este estilo, tengo 50 temas propios\r\nlistos para tocar...  interesados? escribanme a cuarta_d@hotmail.com\r\n\r\n\r\nIntro y estrofas:\r\nG---------------------------------------------|\r\nD---------------------------------------------|\r\nA---------2-2-------------2-2-----------------|\r\nE-0-0-3-5-----5-5-0-0-3-5-----5-5------(x vs.)|\r\n\r\n\r\nEstribillo:\r\nG-------------------------------------------------------|\r\nD-------------------------------------------------------|\r\nA----------------------------------------------2-2------|\r\nE-3--8--7--5--3--1-(vuelve a estrofa)-0-0-3-5-----5-5---|\r\n\r\nDurante 2do, 3er estribillo y solo:\r\n\r\nG----------------------------------------------------------------------|\r\nD----------------------------------------------------------------------|\r\nA---------------------","Notas":[]}]}