{"PartesCancion":[{"Texto":"Con (","Notas":[]},{"Texto":"","Notas":[{"Nombre":"C/A","NumeroNota":0,"NombreNota":"A","Mayor":true,"NumeroModificador":0,"Duracion":0},{"Nombre":"D/A","NumeroNota":0,"NombreNota":"A","Mayor":true,"NumeroModificador":0,"Duracion":0}]},{"Texto":")x4\nTodos quieren magia en las venas\nTodos quieren,quieren,quieren y quieren\nCuanto vale esa masita,cuanto vale ese vacio\n\n","Notas":[]},{"Texto":"","Notas":[{"Nombre":"E","NumeroNota":7,"NombreNota":"E","Mayor":true,"NumeroModificador":0,"Duracion":0},{"Nombre":"D/F#","NumeroNota":9,"NombreNota":"F#","Mayor":true,"NumeroModificador":0,"Duracion":0},{"Nombre":"C","NumeroNota":3,"NombreNota":"C","Mayor":true,"NumeroModificador":0,"Duracion":0}]},{"Texto":"    \n Soy la mosca porte\u00F1a,\n","Notas":[]},{"Texto":"","Notas":[{"Nombre":"E","NumeroNota":7,"NombreNota":"E","Mayor":true,"NumeroModificador":0,"Duracion":0},{"Nombre":"D/F#","NumeroNota":9,"NombreNota":"F#","Mayor":true,"NumeroModificador":0,"Duracion":0},{"Nombre":"C","NumeroNota":3,"NombreNota":"C","Mayor":true,"NumeroModificador":0,"Duracion":0}]},{"Texto":"\n que no te deja dormir\n","Notas":[]},{"Texto":"","Notas":[{"Nombre":"E","NumeroNota":7,"NombreNota":"E","Mayor":true,"NumeroModificador":0,"Duracion":0},{"Nombre":"D/F#","NumeroNota":9,"NombreNota":"F#","Mayor":true,"NumeroModificador":0,"Duracion":0},{"Nombre":"C","NumeroNota":3,"NombreNota":"C","Mayor":true,"NumeroModificador":0,"Duracion":0}]},{"Texto":"    \n Soy la mosca porte\u00F1a,\n","Notas":[]},{"Texto":"","Notas":[{"Nombre":"E","NumeroNota":7,"NombreNota":"E","Mayor":true,"NumeroModificador":0,"Duracion":0},{"Nombre":"D/F#","NumeroNota":9,"NombreNota":"F#","Mayor":true,"NumeroModificador":0,"Duracion":0},{"Nombre":"C","NumeroNota":3,"NombreNota":"C","Mayor":true,"NumeroModificador":0,"Duracion":0}]},{"Texto":"\n vivo y pienso  para atras\n\nTodos van a trabajar con la cara partida\nVos vas a trabajar y pensando en saludar\nSoy la mosca porte\u00F1a,tengo jojos de hambre\nSoy la mosca porte\u00F1a,que me ahogo en tu cerveza\n\n(Con Riff)\n","Notas":[]}]}