{"renglones":["Cuerdas: 6 5 4 3 2 1","E: 0 X X 4 5 4","Esus4: 0 X X 4 5 5","Emaj7: 0 X X 3 3 3","E7:0 X X 4 2 4","G#m7:3 5 3 3 3 3","Db9-:X 4 3 4 3 x","C#7: X 4 3 4 2 x","B/A: X 0 4 4 4 2","A#dim7:X 1 2 0 2 0","F#m/E: 0 4 4 2 2 2","B7sus4:X 2 4 2 5 2","\n\n\nComo la cigarra\n\nCapo II\n\n","E Emaj7 E7 G Dm ","\nTantas veces me mataron, tantas veces me mor\u00ED\n","G7 C D#7 ","\nsin embargo estoy aqu\u00ED resucitando\n","Bm Dm ","\ngracias doy a la desgracia y la mano con pu\u00F1al\n","E7 Am D7 ","\nporque me mat\u00F3 tan mal\n","G Dm G7 ","\ny segu\u00ED cantando.\n\n","C D ","\nCantando al sol como la cigarra\n","Bm Em ","\ndespu\u00E9s de un a\u00F1o bajo la tierra\n","Am D C ","\nigual que sobreviviente\n","D7 G ","\nque vuelve de la guerra.\n\n","\n\n\ntaron,cuantas... mor\u00ED, sin embargo estoy aqu\u00EDresuci-\n","\n\n\n tando doy...desgracia y a...pu-\n"],"nombre":"como_la_cigarra","banda":"mercedes_sosa","tono":{"NroNota":7,"Modo":"","NroModificador":0},"tempo":108.913,"danceability":0.693}