{"renglones":["E A ","\nUh...uh...uh...\n","E A ","\nI\u0027m in love with this modern world\n","E A ","\nI\u0027m in love with this modern girls\n","E A ","\nI used to love an english girl\n","E A ","\nNow I love a german girl\n\nI used to love an italian girl\nNow I love an argentinian girl\nI used to love this rock \u0026 roll world\nNow I love this suicide world\n ","E ","\nBut there one thing\n","A E A ","\none thing I can\u0027t forget\n","A E "],"nombre":"heroin","banda":"sumo","tono":{"NroNota":7,"Modo":"","NroModificador":0},"tempo":92.035,"danceability":0.609}