{"renglones":["Intro: ","A A Bm7 Bm7 A A Bm7 E A ","\nMi casa es tu casa\n\nSiempre que quieras venir\n","A ","\nMi casa es tu casa\n","Bm7 ","\nMe dijiste sin decir\n","E Bm7 ","\nAc\u00E1 los d\u00EDas se pasan volando\n","E A ","\nAc\u00E1 no importa qu\u00E9 diga el reloj\n\n","A ","\nMi casa es tu casa\n\nLlego y no me quiero ir\n","A ","\nmi casa es tu casa\n\nsiempre que quieras venir\n\nmi casa es tu casa\n ","Bm ","\nme dijiste sin decir\n","Em G ","\nac\u00E1 los d\u00EDas se pasan volando\n","Em G Dm ","\nac\u00E1 no importa que diga el reloj\n","A ","\nmi casa es tu casa\n\nllego y no me quiero ir\n\nmi casa es tu casa\n","Bm ","\nhay un cuarto para mi\n","A A7 Bm A E A ","\nMi casa es tu casa\nSiempre que quieras venir\n","A7 ","\nMi casa es tu casa\n","Bm ","\nMe dijiste sin decir\n ","E Bm ","\nAc\u00E1 los d\u00EDas se pasan volando\n ","E A ","\nAc\u00E1 no importa qu\u00E9 diga el reloj\n\n","A ","\nMi casa es tu casa\nLlego y no me quiero ir\n","A7 ","\nMi casa es tu casa\n ","Bm ","(INTRO)A ","Bm A E7 A ","\nMi casa es tu casa\nSiempre que quieras venir\nMi casa es tu casa\n ","Bm ","\nMe dijiste sin decir\n","E7 Bm ","\nAc\u00E1 los d\u00EDas se pasan volando\n","E7 A ","\nAc\u00E1 no importa qu\u00E9 diga el reloj\n","A ","\nMi casa es tu casa\nLlego y no me quiero ir\nMi casa es tu casa\n ","Bm ","\nHay un cuarto para m\u00ED\n","E7 Bm ","\nAc\u00E1 se lucen todas las estrellas\n","E7 A ","(","A ",") (","Bm ",")\n","\n\nLos acordes a su vez est\u00E1n simplificados en esta transcripci\u00F3n como para\nque sea m\u00E1s f\u00E1cil agarrar la guitarra y tocar de una...\n\n\n","A ","\nMi casa es tu casa siempre que quieras venir\n","A Bm ","\nMi casa es tu casa me dijiste sin decir\n","E Bm ","\nAc\u00E1 los d\u00EDas se pasan volando\n","E A ","\nAc\u00E1 no importa qu\u00E9 diga el reloj\n\n\n","A ","Intro: ","A A Bm7 A E A ","\nMi casa es tu casa\n\nSiempre que quieras venir\n ","A ","\nMi casa es tu casa\n","Bm7 ","\nMe dijiste sin decir\n","E Bm7 ","\nAc\u00E1 los d\u00EDas se pasan volando\n","E A ","\nAc\u00E1 no importa qu\u00E9 diga el reloj\n\n ","A ","\nMi casa es tu casa\n\nLlego y no me quiero ir\n"],"nombre":"mi_casa_tu_casa","banda":"conociendo_rusia","tono":{"NroNota":0,"Modo":"","NroModificador":0},"tempo":82.994,"danceability":0.606}