{"renglones":["Bb Gm Dm7 Bb Gm Dm7 Dm7 "," \nNo tengo nada que perder \nquiero que me ayudes. \nLa gente que te viene a ver \nsolo te destruye. \nSi todo el mundo alrededor \npiensa que estas muerto \nyo veo la transformacion \ny la estoy sintiendo. \n\n","Bb Gm "," \nPero no puedo dejar \n","Dm7 "," \nno puedo dejarte, amor \n","Bb Gm Dm7 "," \nno puedo dejar. \n\n\n"],"nombre":"no_puedo_dejar","banda":"seru_giran","tono":{"NroNota":2,"Modo":"","NroModificador":0},"tempo":114.706,"danceability":0.675}