{"PartesCancion":[{"Texto":"","Notas":[{"Nombre":"A","NumeroNota":0,"NombreNota":"A","Mayor":true,"NumeroModificador":0,"Duracion":0},{"Nombre":"D","NumeroNota":5,"NombreNota":"D","Mayor":true,"NumeroModificador":0,"Duracion":0},{"Nombre":"A","NumeroNota":0,"NombreNota":"A","Mayor":true,"NumeroModificador":0,"Duracion":0},{"Nombre":"D","NumeroNota":5,"NombreNota":"D","Mayor":true,"NumeroModificador":0,"Duracion":0},{"Nombre":"A","NumeroNota":0,"NombreNota":"A","Mayor":true,"NumeroModificador":0,"Duracion":0},{"Nombre":"E","NumeroNota":7,"NombreNota":"E","Mayor":true,"NumeroModificador":0,"Duracion":0},{"Nombre":"A","NumeroNota":0,"NombreNota":"A","Mayor":true,"NumeroModificador":0,"Duracion":0},{"Nombre":"A","NumeroNota":0,"NombreNota":"A","Mayor":true,"NumeroModificador":0,"Duracion":0}]},{"Texto":"\nSomos todos iguales leimos Stephen King\n\u0027Cementerio de animales\u0027 como subnormales,\n ","Notas":[]},{"Texto":"","Notas":[{"Nombre":"D","NumeroNota":5,"NombreNota":"D","Mayor":true,"NumeroModificador":0,"Duracion":0},{"Nombre":"A","NumeroNota":0,"NombreNota":"A","Mayor":true,"NumeroModificador":0,"Duracion":0}]},{"Texto":"\nhasta le\u00EDmos Christine, hasta le\u00EDmos it\n          ","Notas":[]},{"Texto":"","Notas":[{"Nombre":"E","NumeroNota":7,"NombreNota":"E","Mayor":true,"NumeroModificador":0,"Duracion":0}]},{"Texto":"\npor eso show me your shit,\n                     ","Notas":[]},{"Texto":"","Notas":[{"Nombre":"A","NumeroNota":0,"NombreNota":"A","Mayor":true,"NumeroModificador":0,"Duracion":0}]},{"Texto":"\nshow me your shit,mam\u00E1.\n\n    ","Notas":[]},{"Texto":"","Notas":[{"Nombre":"A","NumeroNota":0,"NombreNota":"A","Mayor":true,"NumeroModificador":0,"Duracion":0}]},{"Texto":"                    \nViajamos por el mundo, fuimos a Par\u00EDs,\na Jerusal\u00E9n y a Oporto.\n          ","Notas":[]},{"Texto":"","Notas":[{"Nombre":"D","NumeroNota":5,"NombreNota":"D","Mayor":true,"NumeroModificador":0,"Duracion":0}]},{"Texto":"\nLameme el orto, en el buen sentido,\n          ","Notas":[]},{"Texto":"","Notas":[{"Nombre":"A","NumeroNota":0,"NombreNota":"A","Mayor":true,"NumeroModificador":0,"Duracion":0}]},{"Texto":"\nlameme el orto, no est\u00E1 prohibido.\n      ","Notas":[]}]}