{"PartesCancion":[{"Texto":"","Notas":[{"Nombre":"RE","NumeroNota":5,"NombreNota":"RE","Mayor":true,"NumeroModificador":0,"Duracion":0},{"Nombre":"SIm","NumeroNota":2,"NombreNota":"SI","Mayor":false,"NumeroModificador":0,"Duracion":0}]},{"Texto":"\nPronto cuando no est\u00E9 en este lugar \n      ","Notas":[]},{"Texto":"","Notas":[{"Nombre":"SIm7","NumeroNota":2,"NombreNota":"SI","Mayor":false,"NumeroModificador":7,"Duracion":0},{"Nombre":"SOL","NumeroNota":10,"NombreNota":"SOL","Mayor":true,"NumeroModificador":0,"Duracion":0}]},{"Texto":"                        \ndonde nac\u00ED, donde no aprend\u00ED a vivir,\n                   ","Notas":[]},{"Texto":"","Notas":[{"Nombre":"LA","NumeroNota":0,"NombreNota":"LA","Mayor":true,"NumeroModificador":0,"Duracion":0},{"Nombre":"LA7","NumeroNota":0,"NombreNota":"LA","Mayor":true,"NumeroModificador":7,"Duracion":0}]},{"Texto":"      \nte vas a acordar de m\u00ED.\n\nPerd\u00F3n si alguna vez \nno me di cuenta y no estabas contenta\ntampoco estuve ah\u00ED\nno te vi otra vez.\n\nY ciego, ciego, no supe ver \nsordomudo y sin aliento\ny en el viento me perd\u00ED,\nme vol\u00E9, me fui volando.\n\nVolando a donde nunca se vuelve sin volar\npero no s\u00E9 volar,\nni s\u00E9 manejar\n","Notas":[]}]}