{"PartesCancion":[{"Texto":"Intro: ","Notas":[]},{"Texto":"","Notas":[{"Nombre":"Em","NumeroNota":7,"NombreNota":"E","Mayor":false,"NumeroModificador":0,"Duracion":0},{"Nombre":"C","NumeroNota":3,"NombreNota":"C","Mayor":true,"NumeroModificador":0,"Duracion":0},{"Nombre":"D","NumeroNota":5,"NombreNota":"D","Mayor":true,"NumeroModificador":0,"Duracion":0},{"Nombre":"Em","NumeroNota":7,"NombreNota":"E","Mayor":false,"NumeroModificador":0,"Duracion":0}]},{"Texto":" (bis) \n\n","Notas":[]},{"Texto":"","Notas":[{"Nombre":"Em","NumeroNota":7,"NombreNota":"E","Mayor":false,"NumeroModificador":0,"Duracion":0},{"Nombre":"C","NumeroNota":3,"NombreNota":"C","Mayor":true,"NumeroModificador":0,"Duracion":0}]},{"Texto":" \nTodas las canciones son iguales \n\n  ","Notas":[]},{"Texto":"","Notas":[{"Nombre":"D","NumeroNota":5,"NombreNota":"D","Mayor":true,"NumeroModificador":0,"Duracion":0},{"Nombre":"Em","NumeroNota":7,"NombreNota":"E","Mayor":false,"NumeroModificador":0,"Duracion":0}]},{"Texto":" \ny parece que hablan siempre de lo mismo ya \n\n       ","Notas":[]},{"Texto":"","Notas":[{"Nombre":"Em","NumeroNota":7,"NombreNota":"E","Mayor":false,"NumeroModificador":0,"Duracion":0},{"Nombre":"C","NumeroNota":3,"NombreNota":"C","Mayor":true,"NumeroModificador":0,"Duracion":0}]},{"Texto":"               \npero igual existe un abismo \n\n               ","Notas":[]},{"Texto":"","Notas":[{"Nombre":"D","NumeroNota":5,"NombreNota":"D","Mayor":true,"NumeroModificador":0,"Duracion":0},{"Nombre":"Em","NumeroNota":7,"NombreNota":"E","Mayor":false,"NumeroModificador":0,"Duracion":0}]},{"Texto":" \nentre las canciones y la realidad. \n\n\u00BFCu\u00E1l es? \n\nEst\u00E1n las que dan la sensaci\u00F3n \nde poder detener el tiempo por un instante \ny cargan el esp\u00EDritu de gente extra\u00F1a \na un coraz\u00F3n ausente no se le enga\u00F1a. \n","Notas":[]}]}