{"PartesCancion":[{"Texto":"","Notas":[{"Nombre":"Dm","NumeroNota":5,"NombreNota":"D","Mayor":false,"NumeroModificador":0,"Duracion":0},{"Nombre":"Bb","NumeroNota":2,"NombreNota":"B","Mayor":true,"NumeroModificador":0,"Duracion":0},{"Nombre":"A7","NumeroNota":0,"NombreNota":"A","Mayor":true,"NumeroModificador":7,"Duracion":0}]},{"Texto":"\nSi la cintura es un junco\n       ","Notas":[]},{"Texto":"","Notas":[{"Nombre":"Gm","NumeroNota":10,"NombreNota":"G","Mayor":false,"NumeroModificador":0,"Duracion":0},{"Nombre":"C7","NumeroNota":3,"NombreNota":"C","Mayor":true,"NumeroModificador":7,"Duracion":0},{"Nombre":"F","NumeroNota":8,"NombreNota":"F","Mayor":true,"NumeroModificador":0,"Duracion":0}]},{"Texto":"\nY la boca es colora   da,\n   ","Notas":[]},{"Texto":"","Notas":[{"Nombre":"G","NumeroNota":10,"NombreNota":"G","Mayor":true,"NumeroModificador":0,"Duracion":0},{"Nombre":"F","NumeroNota":8,"NombreNota":"F","Mayor":true,"NumeroModificador":0,"Duracion":0}]},{"Texto":"\nSi son los ojos retintos\n       ","Notas":[]},{"Texto":"","Notas":[{"Nombre":"A7","NumeroNota":0,"NombreNota":"A","Mayor":true,"NumeroModificador":7,"Duracion":0},{"Nombre":"Dm","NumeroNota":5,"NombreNota":"D","Mayor":false,"NumeroModificador":0,"Duracion":0}]},{"Texto":"\nEsa moza es tucumana\n","Notas":[]},{"Texto":"","Notas":[{"Nombre":"Bb","NumeroNota":2,"NombreNota":"B","Mayor":true,"NumeroModificador":0,"Duracion":0},{"Nombre":"Bb/A","NumeroNota":0,"NombreNota":"A","Mayor":true,"NumeroModificador":0,"Duracion":0},{"Nombre":"G7","NumeroNota":10,"NombreNota":"G","Mayor":true,"NumeroModificador":7,"Duracion":0}]},{"Texto":"\nSi son los ojos retintos\n      ","Notas":[]},{"Texto":"","Notas":[{"Nombre":"A7","NumeroNota":0,"NombreNota":"A","Mayor":true,"NumeroModificador":7,"Duracion":0},{"Nombre":"Dm","NumeroNota":5,"NombreNota":"D","Mayor":false,"NumeroModificador":0,"Duracion":0}]},{"Texto":"\nEsa moza es tucumana.\n\n\nSi es dulce como esa ni\u00F1a\nY airosa cuando la bailan,\nSi te gana el coraz\u00F3n\nEsa zamba es tucumana.- X2\n\n\n","Notas":[]},{"Texto":"","Notas":[{"Nombre":"SIm","NumeroNota":2,"NombreNota":"SI","Mayor":false,"NumeroModificador":0,"Duracion":0}]},{"Texto":"     (","Notas":[]},{"Texto":"","Notas":[{"Nombre":"SOL","NumeroNota":10,"NombreNota":"SOL","Mayor":true,"NumeroModificador":0,"Duracion":0}]},{"Texto":")           ","Notas":[]},{"Texto":"","Notas":[{"Nombre":"FA#","NumeroNota":9,"NombreNota":"FA#","Mayor":true,"NumeroModificador":0,"Duracion":0}]},{"Texto":"\nSi la cintura es un junco\n      ","Notas":[]},{"Texto":"","Notas":[{"Nombre":"MIm","NumeroNota":7,"NombreNota":"MI","Mayor":false,"NumeroModificador":0,"Duracion":0}]},{"Texto":"      (","Notas":[]},{"Texto":"","Notas":[{"Nombre":"LA","NumeroNota":0,"NombreNota":"LA","Mayor":true,"NumeroModificador":0,"Duracion":0}]},{"Texto":")   ","Notas":[]},{"Texto":"","Notas":[{"Nombre":"RE","NumeroNota":5,"NombreNota":"RE","Mayor":true,"NumeroModificador":0,"Duracion":0}]},{"Texto":"\nY la boca es colora   da,\n   ","Notas":[]},{"Texto":"","Notas":[{"Nombre":"MI","NumeroNota":7,"NombreNota":"MI","Mayor":true,"NumeroModificador":0,"Duracion":0},{"Nombre":"RE","NumeroNota":5,"NombreNota":"RE","Mayor":true,"NumeroModificador":0,"Duracion":0}]},{"Texto":"\nSi son los ojos retintos\n       ","Notas":[]},{"Texto":"","Notas":[{"Nombre":"FA#7","NumeroNota":9,"NombreNota":"FA#","Mayor":true,"NumeroModificador":7,"Duracion":0},{"Nombre":"SIm","NumeroNota":2,"NombreNota":"SI","Mayor":false,"NumeroModificador":0,"Duracion":0}]},{"Texto":"\nEsa moza es tucumana\n","Notas":[]},{"Texto":"","Notas":[{"Nombre":"SOL","NumeroNota":10,"NombreNota":"SOL","Mayor":true,"NumeroModificador":0,"Duracion":0}]},{"Texto":"         (","Notas":[]},{"Texto":"","Notas":[{"Nombre":"LA7","NumeroNota":0,"NombreNota":"LA","Mayor":true,"NumeroModificador":7,"Duracion":0}]},{"Texto":")    ","Notas":[]},{"Texto":"","Notas":[{"Nombre":"RE","NumeroNota":5,"NombreNota":"RE","Mayor":true,"NumeroModificador":0,"Duracion":0}]},{"Texto":"\nSi son los ojos retintos\n      ","Notas":[]},{"Texto":"","Notas":[{"Nombre":"FA#7","NumeroNota":9,"NombreNota":"FA#","Mayor":true,"NumeroModificador":7,"Duracion":0},{"Nombre":"SIm","NumeroNota":2,"NombreNota":"SI","Mayor":false,"NumeroModificador":0,"Duracion":0}]},{"Texto":"\nEsa moza es tucumana.\n\n\nSi es dulce como esa ni\u00F1a\nY airosa cuando la bailan,\nSi te gana el coraz\u00F3n\nEsa zamba es tucumana.- X2\n\n\n","Notas":[]}]}