{"PartesCancion":[{"Texto":"E/G#:    4x245x","Notas":[]},{"Texto":"G#m/B:   x2x444 o 7x9897","Notas":[]},{"Texto":"Cdimm:   x3424x o 8x787x","Notas":[]},{"Texto":"Bsus:    02445x","Notas":[]},{"Texto":"Bsus7/E: 024252","Notas":[]},{"Texto":"E/D#:    xx1100","Notas":[]},{"Texto":"Caug:    x32110","Notas":[]},{"Texto":"E/D:     xx0100 o 50454","Notas":[]},{"Texto":"\n\nIntro: ","Notas":[]},{"Texto":"","Notas":[{"Nombre":"E","NumeroNota":7,"NombreNota":"E","Mayor":true,"NumeroModificador":0,"Duracion":0},{"Nombre":"E/G#","NumeroNota":11,"NombreNota":"G#","Mayor":true,"NumeroModificador":0,"Duracion":0},{"Nombre":"A","NumeroNota":0,"NombreNota":"A","Mayor":true,"NumeroModificador":0,"Duracion":0},{"Nombre":"C#m","NumeroNota":4,"NombreNota":"C#","Mayor":false,"NumeroModificador":0,"Duracion":0},{"Nombre":"G#m/B","NumeroNota":11,"NombreNota":"G#","Mayor":false,"NumeroModificador":0,"Duracion":0},{"Nombre":"Amaj7","NumeroNota":0,"NombreNota":"A","Mayor":false,"NumeroModificador":7,"Duracion":0}]},{"Texto":" / ","Notas":[]},{"Texto":"","Notas":[{"Nombre":"B","NumeroNota":2,"NombreNota":"B","Mayor":true,"NumeroModificador":0,"Duracion":0},{"Nombre":"Cdimm","NumeroNota":3,"NombreNota":"C","Mayor":false,"NumeroModificador":0,"Duracion":0},{"Nombre":"C#m","NumeroNota":4,"NombreNota":"C#","Mayor":false,"NumeroModificador":0,"Duracion":0},{"Nombre":"F#","NumeroNota":9,"NombreNota":"F#","Mayor":true,"NumeroModificador":0,"Duracion":0}]},{"Texto":" / ","Notas":[]},{"Texto":"","Notas":[{"Nombre":"A","NumeroNota":0,"NombreNota":"A","Mayor":true,"NumeroModificador":0,"Duracion":0},{"Nombre":"Bsus","NumeroNota":2,"NombreNota":"B","Mayor":true,"NumeroModificador":0,"Duracion":0},{"Nombre":"B","NumeroNota":2,"NombreNota":"B","Mayor":true,"NumeroModificador":0,"Duracion":0},{"Nombre":"E","NumeroNota":7,"NombreNota":"E","Mayor":true,"NumeroModificador":0,"Duracion":0},{"Nombre":"Bsus7/E","NumeroNota":2,"NombreNota":"B","Mayor":true,"NumeroModificador":7,"Duracion":0},{"Nombre":"E","NumeroNota":7,"NombreNota":"E","Mayor":true,"NumeroModificador":0,"Duracion":0},{"Nombre":"E","NumeroNota":7,"NombreNota":"E","Mayor":true,"NumeroModificador":0,"Duracion":0},{"Nombre":"E/G#","NumeroNota":11,"NombreNota":"G#","Mayor":true,"NumeroModificador":0,"Duracion":0},{"Nombre":"A","NumeroNota":0,"NombreNota":"A","Mayor":true,"NumeroModificador":0,"Duracion":0}]},{"Texto":"\n Ni \u00E1ngel con alas negras, ni profeta del vicio\n","Notas":[]},{"Texto":"","Notas":[{"Nombre":"C#m","NumeroNota":4,"NombreNota":"C#","Mayor":false,"NumeroModificador":0,"Duracion":0},{"Nombre":"G#m/B","NumeroNota":11,"NombreNota":"G#","Mayor":false,"NumeroModificador":0,"Duracion":0},{"Nombre":"A","NumeroNota":0,"NombreNota":"A","Mayor":true,"NumeroModificador":0,"Duracion":0},{"Nombre":"A6","NumeroNota":0,"NombreNota":"A","Mayor":true,"NumeroModificador":0,"Duracion":0},{"Nombre":"A","NumeroNota":0,"NombreNota":"A","Mayor":true,"NumeroModificador":0,"Duracion":0}]},{"Texto":"\n  Ni h\u00E9roe en las barricadas, ni ocupa, ni esquirol\n","Notas":[]},{"Texto":"","Notas":[{"Nombre":"B","NumeroNota":2,"NombreNota":"B","Mayor":true,"NumeroModificador":0,"Duracion":0},{"Nombre":"Cdimm","NumeroNota":3,"NombreNota":"C","Mayor":false,"NumeroModificador":0,"Duracion":0},{"Nombre":"C#m","NumeroNota":4,"NombreNota":"C#","Mayor":false,"NumeroModificador":0,"Duracion":0}]},{"Texto":"\n Ni rey de los suburbios, ni flor   del precipicio\n","Notas":[]},{"Texto":"","Notas":[{"Nombre":"A","NumeroNota":0,"NombreNota":"A","Mayor":true,"NumeroModificador":0,"Duracion":0},{"Nombre":"Bsus","NumeroNota":2,"NombreNota":"B","Mayor":true,"NumeroModificador":0,"Duracion":0},{"Nombre":"E","NumeroNota":7,"NombreNota":"E","Mayor":true,"NumeroModificador":0,"Duracion":0}]},{"Texto":"\n Ni cantante de orquesta, ni el Dylan espa\u00F1ol\n\n","Notas":[]},{"Texto":"","Notas":[{"Nombre":"MI","NumeroNota":7,"NombreNota":"MI","Mayor":true,"NumeroModificador":0,"Duracion":0},{"Nombre":"LA","NumeroNota":0,"NombreNota":"LA","Mayor":true,"NumeroModificador":0,"Duracion":0},{"Nombre":"DO#m","NumeroNota":4,"NombreNota":"DO#","Mayor":false,"NumeroModificador":0,"Duracion":0},{"Nombre":"SI","NumeroNota":2,"NombreNota":"SI","Mayor":true,"NumeroModificador":0,"Duracion":0},{"Nombre":"LA","NumeroNota":0,"NombreNota":"LA","Mayor":true,"NumeroModificador":0,"Duracion":0},{"Nombre":"SI","NumeroNota":2,"NombreNota":"SI","Mayor":true,"NumeroModificador":0,"Duracion":0},{"Nombre":"DOm","NumeroNota":3,"NombreNota":"DO","Mayor":false,"NumeroModificador":0,"Duracion":0},{"Nombre":"DO#m","NumeroNota":4,"NombreNota":"DO#","Mayor":false,"NumeroModificador":0,"Duracion":0},{"Nombre":"FA#","NumeroNota":9,"NombreNota":"FA#","Mayor":true,"NumeroModificador":0,"Duracion":0},{"Nombre":"LA","NumeroNota":0,"NombreNota":"LA","Mayor":true,"NumeroModificador":0,"Duracion":0},{"Nombre":"SI","NumeroNota":2,"NombreNota":"SI","Mayor":true,"NumeroModificador":0,"Duracion":0},{"Nombre":"MI","NumeroNota":7,"NombreNota":"MI","Mayor":true,"NumeroModificador":0,"Duracion":0},{"Nombre":"MI","NumeroNota":7,"NombreNota":"MI","Mayor":true,"NumeroModificador":0,"Duracion":0}]},{"Texto":"\nNi \u00E1ngel con alas negras\n      ","Notas":[]},{"Texto":"","Notas":[{"Nombre":"LA","NumeroNota":0,"NombreNota":"LA","Mayor":true,"NumeroModificador":0,"Duracion":0}]},{"Texto":"\nni profeta del vicio\n","Notas":[]},{"Texto":"","Notas":[{"Nombre":"DO#m","NumeroNota":4,"NombreNota":"DO#","Mayor":false,"NumeroModificador":0,"Duracion":0},{"Nombre":"SOL#m","NumeroNota":11,"NombreNota":"SOL#","Mayor":false,"NumeroModificador":0,"Duracion":0}]},{"Texto":"\nni h\u00E9roe en las barricadas\n      ","Notas":[]},{"Texto":"","Notas":[{"Nombre":"LA","NumeroNota":0,"NombreNota":"LA","Mayor":true,"NumeroModificador":0,"Duracion":0}]},{"Texto":"\nni ocupa, ni esquirol\n","Notas":[]},{"Texto":"","Notas":[{"Nombre":"SI","NumeroNota":2,"NombreNota":"SI","Mayor":true,"NumeroModificador":0,"Duracion":0}]},{"Texto":"\nni rey de los suburbios\n      ","Notas":[]},{"Texto":"","Notas":[{"Nombre":"DO#m","NumeroNota":4,"NombreNota":"DO#","Mayor":false,"NumeroModificador":0,"Duracion":0}]},{"Texto":"\nni flor del precipicio\n","Notas":[]},{"Texto":"","Notas":[{"Nombre":"LA","NumeroNota":0,"NombreNota":"LA","Mayor":true,"NumeroModificador":0,"Duracion":0},{"Nombre":"SI","NumeroNota":2,"NombreNota":"SI","Mayor":true,"NumeroModificador":0,"Duracion":0}]},{"Texto":"\nni cantante de orquesta\n            ","Notas":[]},{"Texto":"","Notas":[{"Nombre":"MI","NumeroNota":7,"NombreNota":"MI","Mayor":true,"NumeroModificador":0,"Duracion":0}]},{"Texto":"\nni el Dylan espa\u00F1ol\n","Notas":[]},{"Texto":"","Notas":[{"Nombre":"E","NumeroNota":7,"NombreNota":"E","Mayor":true,"NumeroModificador":0,"Duracion":0},{"Nombre":"A","NumeroNota":0,"NombreNota":"A","Mayor":true,"NumeroModificador":0,"Duracion":0},{"Nombre":"C#m","NumeroNota":4,"NombreNota":"C#","Mayor":false,"NumeroModificador":0,"Duracion":0},{"Nombre":"B","NumeroNota":2,"NombreNota":"B","Mayor":true,"NumeroModificador":0,"Duracion":0},{"Nombre":"A","NumeroNota":0,"NombreNota":"A","Mayor":true,"NumeroModificador":0,"Duracion":0},{"Nombre":"E","NumeroNota":7,"NombreNota":"E","Mayor":true,"NumeroModificador":0,"Duracion":0},{"Nombre":"B","NumeroNota":2,"NombreNota":"B","Mayor":true,"NumeroModificador":0,"Duracion":0},{"Nombre":"C#m","NumeroNota":4,"NombreNota":"C#","Mayor":false,"NumeroModificador":0,"Duracion":0},{"Nombre":"A","NumeroNota":0,"NombreNota":"A","Mayor":true,"NumeroModificador":0,"Duracion":0},{"Nombre":"B","NumeroNota":2,"NombreNota":"B","Mayor":true,"NumeroModificador":0,"Duracion":0},{"Nombre":"E","NumeroNota":7,"NombreNota":"E","Mayor":true,"NumeroModificador":0,"Duracion":0},{"Nombre":"E","NumeroNota":7,"NombreNota":"E","Mayor":true,"NumeroModificador":0,"Duracion":0},{"Nombre":"A","NumeroNota":0,"NombreNota":"A","Mayor":true,"NumeroModificador":0,"Duracion":0}]},{"Texto":"\nNi \u00E1ngel con alas negras, ni profeta del vicio\n","Notas":[]},{"Texto":"","Notas":[{"Nombre":"C#m","NumeroNota":4,"NombreNota":"C#","Mayor":false,"NumeroModificador":0,"Duracion":0},{"Nombre":"A","NumeroNota":0,"NombreNota":"A","Mayor":true,"NumeroModificador":0,"Duracion":0}]},{"Texto":"\nni h\u00E9roe en las barricadas, ni ocupa, ni esquirol\n","Notas":[]},{"Texto":"","Notas":[{"Nombre":"G#","NumeroNota":11,"NombreNota":"G#","Mayor":true,"NumeroModificador":0,"Duracion":0},{"Nombre":"C#m","NumeroNota":4,"NombreNota":"C#","Mayor":false,"NumeroModificador":0,"Duracion":0}]},{"Texto":"\nni rey de los suburbios, ni flor del precipicio\n","Notas":[]},{"Texto":"","Notas":[{"Nombre":"A","NumeroNota":0,"NombreNota":"A","Mayor":true,"NumeroModificador":0,"Duracion":0},{"Nombre":"B","NumeroNota":2,"NombreNota":"B","Mayor":true,"NumeroModificador":0,"Duracion":0},{"Nombre":"E","NumeroNota":7,"NombreNota":"E","Mayor":true,"NumeroModificador":0,"Duracion":0}]},{"Texto":"\nni cantante de orquesta, ni el Dylan espa\u00F1ol\n\n","Notas":[]},{"Texto":"","Notas":[{"Nombre":"E","NumeroNota":7,"NombreNota":"E","Mayor":true,"NumeroModificador":0,"Duracion":0},{"Nombre":"A","NumeroNota":0,"NombreNota":"A","Mayor":true,"NumeroModificador":0,"Duracion":0}]},{"Texto":"\nNi el abajo firmante, ni vendedor de humo\n","Notas":[]},{"Texto":"","Notas":[{"Nombre":"C#m","NumeroNota":4,"NombreNota":"C#","Mayor":false,"NumeroModificador":0,"Duracion":0},{"Nombre":"A","NumeroNota":0,"NombreNota":"A","Mayor":true,"NumeroModificador":0,"Duracion":0}]},{"Texto":"\nni juglar del asfalto, ni rojo de sal\u00F3n\n","Notas":[]},{"Texto":"","Notas":[{"Nombre":"G#","NumeroNota":11,"NombreNota":"G#","Mayor":true,"NumeroModificador":0,"Duracion":0},{"Nombre":"C#m","NumeroNota":4,"NombreNota":"C#","Mayor":false,"NumeroModificador":0,"Duracion":0}]},{"Texto":"\nni escondo la pasi\u00F3n, ni la perfumo\n","Notas":[]},{"Texto":"","Notas":[{"Nombre":"A","NumeroNota":0,"NombreNota":"A","Mayor":true,"NumeroModificador":0,"Duracion":0},{"Nombre":"B","NumeroNota":2,"NombreNota":"B","Mayor":true,"NumeroModificador":0,"Duracion":0},{"Nombre":"E","NumeroNota":7,"NombreNota":"E","Mayor":true,"NumeroModificador":0,"Duracion":0}]},{"Texto":"\nni he quemado mis naves, ni s\u00E9 pedir perd\u00F3n\n\n","Notas":[]}]}