{"renglones":["Intro: ","Am Am Dm Dm G G C E7 Am ","Cansado de buscar","Dm ","Y herido en mil fracasosHab\u00EDa decidido","G7 ","Caminar en soledadSin pena ni pasi\u00F3n","C ","Y en eso apareciste","E7 ","Todo cambio","Am ","Me fui acercando a vos","LAm REm ","Cansado de buscar, y herido en mil fracasos","SOL","habia decidido caminar en soledad, ","DO","sin penas ni pasion, y en eso apareciste","MI","todo cambio.Me fui acercando a vos con suma precaucion,midiendo cada faso, retorcido en mi interior,librandome de miedos y de deudas del ayerpara intentar de nuevo, volver a creer","REm ","Me entregue y no me arrepiento","LAm "," nunca estuve asi de contento","REm ","y me paso el dia cantando,","MI"," Cansado de buscar, y herido en mil fracasos"," Hab\u00EDa decidido caminar en soledad"],"nombre":"amor","banda":"autenticos","tono":{"NroNota":0,"Modo":"m","NroModificador":0},"tempo":92.869,"danceability":0.597}