{"renglones":["Am Em "," x2 ","Am Em ","Dentro de una canci\u00F3n esta la vida ","Am Em ","dentro de una canci\u00F3n llegar\u00E1 ma\u00F1ana ","Am Em ","dentro de una canci\u00F3n se estira la cuerda del hambre","Am Em ","cabe poco dentro de una canci\u00F3n. ","C ","Entra lo que sale dentro de una canci\u00F3n ","G D ","sobra lo que cabe dentro de una canci\u00F3n"],"nombre":"dentro_de_una_cancion","banda":"andres_calamaro","tono":{"NroNota":0,"Modo":"m","NroModificador":0},"tempo":104.993,"danceability":0.635}