{"renglones":["Am Dm E Am Dm E Am Dm E Am Dm E ","Estrofa:","Am Dm E ","Mi h\u00E9roe es, la gran Bestia Pop,","Am Dm E ","que enciende en sue\u00F1os, la vigilia","Am Dm E Am Dm E ","que antes que cuente diez, dormir\u00E1.Estribillo:","Am F E Am F E A "," brillar ","MI "," amor, vamos a brillar mi amor","Am F E Am F E A "," brillar ","MI "," amor, vamos a brillar mi amor."],"nombre":"la_bestia_pop","banda":"palmeras","tono":{"NroNota":0,"Modo":"m","NroModificador":0},"tempo":130.009,"danceability":0.763}