{"renglones":["E ","Ahora que estoy vac\u00EDo","F# ","ahora que no hay canci\u00F3n","A E ","toda la luna cabe en m\u00ED.","E ","Ahora que soy silbido","F# ","de alguien que sale a andar","A E ","veo otro cielo alrededor.","C#m ","Todos esos deseos","G# ","de noche fr\u00EDa y de alcohol","A E ","hoy te los quiero regalar.","E ","Ahora que estoy vac\u00EDo","F# ","ahora que no hay canci\u00F3n","A E ","toda la luna cabe en m\u00ED.","E ","Ahora que soy silbido","F# ","de alguien que sale a andar","A E ","veo otro cielo alrededor.","C#m ","Todos esos deseos","G# ","de noche fr\u00EDa y de alcohol","A E ","hoy te los quiero regalar.","E "," Ahora que estoy vaci\u00F3","F# "," Ahora que no hay canci\u00F3n","A E "," Toda la luna cabe en m\u00ED","E "," Ahora que soy silbido","F# "," De alguien que sale a andar","A E "," Veo otro cielo alrededor","C#m "," Todos esos deseos","G#m "," De noche fr\u00EDa de alcohol","A E "," Hoy te los quiero regalar","E ","Ahora que estoy vac\u00EDo","F# ","ahora que no hay canci\u00F3n","A E ","toda la luna cabe en m\u00ED.","E ","Ahora que soy silbido","F# ","de alguien que sale a andar","A E ","veo otro cielo alrrededor.","C#m ","Todos esos deseos","G#m ","de noche fr\u00EDa y de alcohol","A E ","hoy te los quiero regalar.","E F#7 ","Ahora que estoy vac\u00EDo ","A ","ahora que no hay canci\u00F3n","E ","toda la luna cabe en m\u00ED.","E F#7 ","Ahora que soy silbido ","A7 ","de alguien que sale a andar ","E ","veo otro cielo alrrededor.","C#m ","Todos esos deseos","G#7 ","de noche fr\u00EDa y de alcohol","A E ","hoy te los quiero regalar."],"nombre":"pacifico","banda":"piojos","tono":{"NroNota":7,"Modo":"","NroModificador":0},"tempo":144.978,"danceability":0.503}