{"PartesCancion":[{"Texto":"e|------------------------------|","Notas":[]},{"Texto":"B|-----------------------8-8----|","Notas":[]},{"Texto":"G|----5----7-7------5-----------|","Notas":[]},{"Texto":"D|--5---5---------5---5---------|","Notas":[]},{"Texto":"A|------------------------------|","Notas":[]},{"Texto":"E|------------------------------|","Notas":[]},{"Texto":"","Notas":[{"Nombre":"Em","NumeroNota":7,"NombreNota":"E","Mayor":false,"NumeroModificador":0,"Duracion":0}]},{"Texto":"\nEl perro bobi es un servicio de amor\n","Notas":[]},{"Texto":"","Notas":[{"Nombre":"Bm","NumeroNota":2,"NombreNota":"B","Mayor":false,"NumeroModificador":0,"Duracion":0}]},{"Texto":"\na todo rock,\n","Notas":[]},{"Texto":"","Notas":[{"Nombre":"Em","NumeroNota":7,"NombreNota":"E","Mayor":false,"NumeroModificador":0,"Duracion":0}]},{"Texto":"\ncanta como un le\u00F3n, pero es el m\u00E1s salm\u00F3n\n","Notas":[]},{"Texto":"","Notas":[{"Nombre":"Bm","NumeroNota":2,"NombreNota":"B","Mayor":false,"NumeroModificador":0,"Duracion":0}]},{"Texto":"\nde la ciudad,\n\n","Notas":[]},{"Texto":"","Notas":[{"Nombre":"Am","NumeroNota":0,"NombreNota":"A","Mayor":false,"NumeroModificador":0,"Duracion":0},{"Nombre":"Em","NumeroNota":7,"NombreNota":"E","Mayor":false,"NumeroModificador":0,"Duracion":0}]},{"Texto":" (riff)\nBailen lo que bailen los dem\u00E1s,\n","Notas":[]},{"Texto":"","Notas":[{"Nombre":"Em","NumeroNota":7,"NombreNota":"E","Mayor":false,"NumeroModificador":0,"Duracion":0}]},{"Texto":"\nEl perro bobi es \n                    ","Notas":[]},{"Texto":"","Notas":[{"Nombre":"Bm","NumeroNota":2,"NombreNota":"B","Mayor":false,"NumeroModificador":0,"Duracion":0}]},{"Texto":"\nun servicio de amor a todo rock,\n","Notas":[]},{"Texto":"","Notas":[{"Nombre":"Em","NumeroNota":7,"NombreNota":"E","Mayor":false,"NumeroModificador":0,"Duracion":0}]},{"Texto":"\ncanta como un le\u00F3n,\n                      ","Notas":[]},{"Texto":"","Notas":[{"Nombre":"Bm","NumeroNota":2,"NombreNota":"B","Mayor":false,"NumeroModificador":0,"Duracion":0}]},{"Texto":"\npero es el m\u00E1s salm\u00F3n de la ciudad,\n\n","Notas":[]},{"Texto":"","Notas":[{"Nombre":"C","NumeroNota":3,"NombreNota":"C","Mayor":true,"NumeroModificador":0,"Duracion":0},{"Nombre":"Em","NumeroNota":7,"NombreNota":"E","Mayor":false,"NumeroModificador":0,"Duracion":0}]},{"Texto":"\nBailen lo que bailen los dem\u00E1s,\n","Notas":[]},{"Texto":"","Notas":[{"Nombre":"C","NumeroNota":3,"NombreNota":"C","Mayor":true,"NumeroModificador":0,"Duracion":0},{"Nombre":"Em","NumeroNota":7,"NombreNota":"E","Mayor":false,"NumeroModificador":0,"Duracion":0}]},{"Texto":"\nbailen lo que bailen los dem\u00E1s.\n\n\n\nChunga combinaci\u00F3n de polvos\nque dar\u00E1n lodo despu\u00E9s,\nm\u00E1gico inter - terror m\u00E1s arma\nblanca en cruda pasi\u00F3n,\n","Notas":[]},{"Texto":"e|-----------------------------------------------------------------------||","Notas":[]},{"Texto":"B|----------------------------9-11-9--------------------9-11-9-----------||","Notas":[]},{"Texto":"G|---8-6---8-6-------8h10h11---------11-10-8---8h10h11---------11-10-----||","Notas":[]},{"Texto":"D|-----------------------------------------------------------------------||","Notas":[]},{"Texto":"A|-------9---------------------------------------------------------------||","Notas":[]},{"Texto":"E|-----------------------------------------------------------------------||","Notas":[]},{"Texto":"\n                                                                         ||(X2)\n","Notas":[]},{"Texto":"e|--------------------------------------------------|                    ||","Notas":[]},{"Texto":"B|----------------11-9----10b--9----11-9----10b-----|                    ||","Notas":[]},{"Texto":"G|---6-8---6-8---------11--------11------11---------|                    ||","Notas":[]},{"Texto":"D|-------8------------------------------------------|                    ||","Notas":[]},{"Texto":"A|--------------------------------------------------|                    ||","Notas":[]},{"Texto":"E|--------------------------------------------------|                    ||","Notas":[]},{"Texto":"\n\n(2)\n","Notas":[]},{"Texto":"e|-------------------------------------------------------|","Notas":[]},{"Texto":"B|---9-7------9-7------------9-7-------9-7------9s11~----|","Notas":[]},{"Texto":"G|-------10-8-----10-8-8~---------10-8-----10-8----------|","Notas":[]},{"Texto":"D|-------------------------------------------------------|","Notas":[]},{"Texto":"A|-------------------------------------------------------|","Notas":[]},{"Texto":"Intro:\r\n\r\ne|--------------------------|-------------------------------------------------|\r\nB|--(5)---(3)-----(5)---(3)-|--5-5h7h8-10-12-10-8-7----5-5h7h8-10-12-10-8-7---|\r\nG|--------------------------|-------------------------------------------------|\r\nD|--------------------------|-------------------------------------------------|\r\nA|--------------------------|-------------------------------------------------|\r\nE|--------------------------|-------------------------------------------------|\r\n\r\ne|--------------------------|---------------------------------------|\r\nB|--(3)---(5)-----(3)---(5)-|--12bp10-8-12b-10---12bp10-8-12b-------|\r\nG|--------------------------|---------------------------------------|\r\nD|--------------------------|---------------------------------------|\r\nA|--------------------------|---------------------------------------|\r\nE|--------------------------|---------------------------------------|\r\n\r\ne|--------------------------|---------------------------------------------","Notas":[]}]}