{"PartesCancion":[{"Texto":"Intro: ","Notas":[]},{"Texto":"","Notas":[{"Nombre":"A","NumeroNota":0,"NombreNota":"A","Mayor":true,"NumeroModificador":0,"Duracion":0},{"Nombre":"A","NumeroNota":0,"NombreNota":"A","Mayor":true,"NumeroModificador":0,"Duracion":0}]},{"Texto":"\nMi carga y mi bota estan vacias ya\n","Notas":[]},{"Texto":"","Notas":[{"Nombre":"A","NumeroNota":0,"NombreNota":"A","Mayor":true,"NumeroModificador":0,"Duracion":0}]},{"Texto":"\nLa noche ha terminado pero no amaneci\u00F3\n","Notas":[]},{"Texto":"","Notas":[{"Nombre":"D","NumeroNota":5,"NombreNota":"D","Mayor":true,"NumeroModificador":0,"Duracion":0}]},{"Texto":"\nEstoy aqu\u00ED sentado solo y muy tranquilo\n","Notas":[]},{"Texto":"","Notas":[{"Nombre":"A","NumeroNota":0,"NombreNota":"A","Mayor":true,"NumeroModificador":0,"Duracion":0}]},{"Texto":"\nEl tren que no se acerca mi pasiencia acab\u00F3\n\n\n           ","Notas":[]},{"Texto":"","Notas":[{"Nombre":"E","NumeroNota":7,"NombreNota":"E","Mayor":true,"NumeroModificador":0,"Duracion":0},{"Nombre":"D","NumeroNota":5,"NombreNota":"D","Mayor":true,"NumeroModificador":0,"Duracion":0},{"Nombre":"A","NumeroNota":0,"NombreNota":"A","Mayor":true,"NumeroModificador":0,"Duracion":0},{"Nombre":"E","NumeroNota":7,"NombreNota":"E","Mayor":true,"NumeroModificador":0,"Duracion":0}]},{"Texto":"\nY aqui estoy,      estoy tirado en la estaci\u00F3n\n\n\n","Notas":[]},{"Texto":"","Notas":[{"Nombre":"A","NumeroNota":0,"NombreNota":"A","Mayor":true,"NumeroModificador":0,"Duracion":0}]},{"Texto":"\nDespu\u00E9s de una gran noche uno no quiere m\u00E1s\n","Notas":[]},{"Texto":"","Notas":[{"Nombre":"A","NumeroNota":0,"NombreNota":"A","Mayor":true,"NumeroModificador":0,"Duracion":0}]},{"Texto":"\nCon ca\u00F1as y aceitunas la pas\u00E9 muy bien\n","Notas":[]},{"Texto":"TIRADO EN LA ESTACION-VIEJAS LOCAS\n\n  Intro (0:09)\ne|-9--7---5--5--\nB|--------------\nG|-9--7---6--6--  X4\nD|--------------\nA|--------------\nE|--------------\n\n\n  riff de al final de cada estrofa\ne|-------------------------------------------------------------\nB|-------------------------------------------------------------\nG|-----5-7--7b-7b-7ba-p5----------------7p5--------------------\nD|-5h7-------------------7-7p5---5h6h7-------------------------\nA|-----------------------------7-------------------------------\nE|-------------------------------------------------------------\n\n\n  primer solo (1:10)\ne|-9--7--9-9----9--7--9-9----9--7--9-9----9--7--9--------------\nB|-------------------------------------------------------------\nG|-9--7--9-9----9--7--9-9----9--7--9-9----9--7--9--------------\nD|-------------------------------------------------------------\nA|-------------------------------------------------------------\nE|-------------------------------------------------------------\n\n\n\ne|-----10---","Notas":[]}]}